MANIFEST.in
changes.txt
license.txt
readme.md
setup.py
nive_cms_design_bs3/__init__.py
nive_cms_design_bs3/elementcss.py
nive_cms_design_bs3/view.py
nive_cms_design_bs3.egg-info/PKG-INFO
nive_cms_design_bs3.egg-info/SOURCES.txt
nive_cms_design_bs3.egg-info/dependency_links.txt
nive_cms_design_bs3.egg-info/not-zip-safe
nive_cms_design_bs3.egg-info/requires.txt
nive_cms_design_bs3.egg-info/top_level.txt
nive_cms_design_bs3/static/jquery-1.10.2.min.js
nive_cms_design_bs3/static/jquery-1.10.2.min.map
nive_cms_design_bs3/static/styles.css
nive_cms_design_bs3/static/bootstrap-3.1.1/config.json
nive_cms_design_bs3/static/bootstrap-3.1.1/css/bootstrap-theme.css
nive_cms_design_bs3/static/bootstrap-3.1.1/css/bootstrap-theme.min.css
nive_cms_design_bs3/static/bootstrap-3.1.1/css/bootstrap.css
nive_cms_design_bs3/static/bootstrap-3.1.1/css/bootstrap.min.css
nive_cms_design_bs3/static/bootstrap-3.1.1/fonts/glyphicons-halflings-regular.eot
nive_cms_design_bs3/static/bootstrap-3.1.1/fonts/glyphicons-halflings-regular.svg
nive_cms_design_bs3/static/bootstrap-3.1.1/fonts/glyphicons-halflings-regular.ttf
nive_cms_design_bs3/static/bootstrap-3.1.1/fonts/glyphicons-halflings-regular.woff
nive_cms_design_bs3/static/bootstrap-3.1.1/js/bootstrap.js
nive_cms_design_bs3/static/bootstrap-3.1.1/js/bootstrap.min.js
nive_cms_design_bs3/static/imgs/arrow.png
nive_cms_design_bs3/static/imgs/download.png
nive_cms_design_bs3/static/imgs/elink.png
nive_cms_design_bs3/static/imgs/logocms.png
nive_cms_design_bs3/static/imgs/logocms2.png
nive_cms_design_bs3/templates/box.pt
nive_cms_design_bs3/templates/code.pt
nive_cms_design_bs3/templates/column.pt
nive_cms_design_bs3/templates/file.pt
nive_cms_design_bs3/templates/image.pt
nive_cms_design_bs3/templates/index.pt
nive_cms_design_bs3/templates/link.pt
nive_cms_design_bs3/templates/media.pt
nive_cms_design_bs3/templates/menublock.pt
nive_cms_design_bs3/templates/news.pt
nive_cms_design_bs3/templates/note.pt
nive_cms_design_bs3/templates/page.pt
nive_cms_design_bs3/templates/root.pt
nive_cms_design_bs3/templates/search.pt
nive_cms_design_bs3/templates/spacer.pt
nive_cms_design_bs3/templates/text.pt
nive_cms_design_bs3/tests/__init__.py
nive_cms_design_bs3/tests/test_configuration.py
